{"cenas":{"1":{"nome":"Master On","comandos":["M4C1:100","M4C2:100","M4C3:100","M4C4:100","M4C5:100"],"triggers":["ATVCENA01"]},"2":{"nome":"Master Off","comandos":["M4C1:000","M4C2:000","M4C3:000","M4C4:000","M4C5:000"],"triggers":["ATVCENA02"]},"3":{"nome":"Cena Festa","comandos":["M1C1:1","M1C2:1","M1C3:1","M1C4:1"],"triggers":["ATVCENA03"]}},"alarmes":{"agendamentos":{},"sunRise":{"cena":"-1","horario":":+00:00"},"sunSet":{"cena":"-1","horario":":+00:00"}},"gateway":{"mac":"54-10-EC-B1-3D-C4","versao":"V3.0.0b","timestamp":"1592586296415","latitude":"0.0","longitude":"0.0","timezone":"0","nome":"Automatize Hall","build":1592586301589},"mapa":{"1":{"tipo":"Rele","versao":"3.0.0b","E":{"1":{"nome":"Entrada 1","funcao":"E>>S","paralelo":{"endereco":"","canal":"","pulsoLongo":""},"automacaoCenas":{"pulsoRapido":"0","pulsoLongo":"0"},"E>>S":"-1"},"2":{"nome":"Entrada 2","funcao":"E>>S","paralelo":{"endereco":"","canal":"","pulsoLongo":""},"automacaoCenas":{"pulsoRapido":"0","pulsoLongo":"0"},"E>>S":"-1"},"3":{"nome":"Entrada 3","funcao":"E>>S","paralelo":{"endereco":"","canal":"","pulsoLongo":""},"automacaoCenas":{"pulsoRapido":"0","pulsoLongo":"0"},"E>>S":"-1"},"4":{"nome":"Entrada 4","funcao":"E>>S","paralelo":{"endereco":"","canal":"","pulsoLongo":""},"automacaoCenas":{"pulsoRapido":"0","pulsoLongo":"0"},"E>>S":"-1"},"5":{"nome":"Entrada 5","funcao":"E>>S","paralelo":{"endereco":"","canal":"","pulsoLongo":""},"automacaoCenas":{"pulsoRapido":"0","pulsoLongo":"0"},"E>>S":"-1"},"6":{"nome":"Entrada 6","funcao":"E>>S","paralelo":{"endereco":"","canal":"","pulsoLongo":""},"automacaoCenas":{"pulsoRapido":"0","pulsoLongo":"0"},"E>>S":"-1"},"7":{"nome":"Entrada 7","funcao":"E>>S","paralelo":{"endereco":"","canal":"","pulsoLongo":""},"automacaoCenas":{"pulsoRapido":"0","pulsoLongo":"0"},"E>>S":"-1"},"8":{"nome":"Entrada 8","funcao":"E>>S","paralelo":{"endereco":"","canal":"","pulsoLongo":""},"automacaoCenas":{"pulsoRapido":"0","pulsoLongo":"0"},"E>>S":"-1"}},"S":{"1":{"nome":"Centrais","funcao":"Liga/Desliga","timer":{"minutos":"0","segundos":"0","milesimos":"0"},"rampa":"2","presetMax":"100","presetMin":"0","memoriaPreset":"false","lastState":"false","ON/OFF":"false"},"2":{"nome":"Sanca","funcao":"Liga/Desliga","timer":{"minutos":"0","segundos":"0","milesimos":"0"},"rampa":"2","presetMax":"100","presetMin":"0","memoriaPreset":"false","lastState":"false","ON/OFF":"false"},"3":{"nome":"Jardim de Inverno","funcao":"Liga/Desliga","timer":{"minutos":"0","segundos":"0","milesimos":"0"},"rampa":"2","presetMax":"100","presetMin":"0","memoriaPreset":"false","lastState":"false","ON/OFF":"false"},"4":{"nome":"Muro","funcao":"Liga/Desliga","timer":{"minutos":"0","segundos":"0","milesimos":"0"},"rampa":"2","presetMax":"100","presetMin":"0","memoriaPreset":"false","lastState":"false","ON/OFF":"false"},"5":{"nome":"Saida 5","funcao":"Liga/Desliga","timer":{"minutos":"0","segundos":"0","milesimos":"0"},"rampa":"2","presetMax":"100","presetMin":"0","memoriaPreset":"false","lastState":"false","ON/OFF":"false"},"6":{"nome":"Saida 6","funcao":"Liga/Desliga","timer":{"minutos":"0","segundos":"0","milesimos":"0"},"rampa":"2","presetMax":"100","presetMin":"0","memoriaPreset":"false","lastState":"false","ON/OFF":"false"},"7":{"nome":"Saida 7","funcao":"Liga/Desliga","timer":{"minutos":"0","segundos":"0","milesimos":"0"},"rampa":"2","presetMax":"100","presetMin":"0","memoriaPreset":"false","lastState":"false","ON/OFF":"false"},"8":{"nome":"Saida 8","funcao":"Liga/Desliga","timer":{"minutos":"0","segundos":"0","milesimos":"0"},"rampa":"2","presetMax":"100","presetMin":"0","memoriaPreset":"false","lastState":"false","ON/OFF":"false"}},"mapeado":true,"valido":true},"2":{"tipo":"Rele","versao":"3.0.0b","E":{"1":{"nome":"Entrada 1","funcao":"E>>S","paralelo":{"endereco":"","canal":"","pulsoLongo":""},"automacaoCenas":{"pulsoRapido":"0","pulsoLongo":"0"},"E>>S":"-1"},"2":{"nome":"Entrada 2","funcao":"E>>S","paralelo":{"endereco":"","canal":"","pulsoLongo":""},"automacaoCenas":{"pulsoRapido":"0","pulsoLongo":"0"},"E>>S":"-1"},"3":{"nome":"Entrada 3","funcao":"E>>S","paralelo":{"endereco":"","canal":"","pulsoLongo":""},"automacaoCenas":{"pulsoRapido":"0","pulsoLongo":"0"},"E>>S":"-1"},"4":{"nome":"Entrada 4","funcao":"E>>S","paralelo":{"endereco":"","canal":"","pulsoLongo":""},"automacaoCenas":{"pulsoRapido":"0","pulsoLongo":"0"},"E>>S":"-1"},"5":{"nome":"Entrada 5","funcao":"E>>S","paralelo":{"endereco":"","canal":"","pulsoLongo":""},"automacaoCenas":{"pulsoRapido":"0","pulsoLongo":"0"},"E>>S":"-1"},"6":{"nome":"Entrada 6","funcao":"E>>S","paralelo":{"endereco":"","canal":"","pulsoLongo":""},"automacaoCenas":{"pulsoRapido":"0","pulsoLongo":"0"},"E>>S":"-1"},"7":{"nome":"Entrada 7","funcao":"E>>S","paralelo":{"endereco":"","canal":"","pulsoLongo":""},"automacaoCenas":{"pulsoRapido":"0","pulsoLongo":"0"},"E>>S":"-1"},"8":{"nome":"Entrada 8","funcao":"E>>S","paralelo":{"endereco":"","canal":"","pulsoLongo":""},"automacaoCenas":{"pulsoRapido":"0","pulsoLongo":"0"},"E>>S":"-1"}},"S":{"1":{"nome":"Saida 1","funcao":"Liga/Desliga","timer":{"minutos":"0","segundos":"0","milesimos":"0"},"rampa":"2","presetMax":"100","presetMin":"0","memoriaPreset":"false","lastState":"false","ON/OFF":"false"},"2":{"nome":"Saida 2","funcao":"Liga/Desliga","timer":{"minutos":"0","segundos":"0","milesimos":"0"},"rampa":"2","presetMax":"100","presetMin":"0","memoriaPreset":"false","lastState":"false","ON/OFF":"false"},"3":{"nome":"Saida 3","funcao":"Liga/Desliga","timer":{"minutos":"0","segundos":"0","milesimos":"0"},"rampa":"2","presetMax":"100","presetMin":"0","memoriaPreset":"false","lastState":"false","ON/OFF":"false"},"4":{"nome":"Saida 4","funcao":"Liga/Desliga","timer":{"minutos":"0","segundos":"0","milesimos":"0"},"rampa":"2","presetMax":"100","presetMin":"0","memoriaPreset":"false","lastState":"false","ON/OFF":"false"},"5":{"nome":"Saida 5","funcao":"Liga/Desliga","timer":{"minutos":"0","segundos":"0","milesimos":"0"},"rampa":"2","presetMax":"100","presetMin":"0","memoriaPreset":"false","lastState":"false","ON/OFF":"false"},"6":{"nome":"Saida 6","funcao":"Liga/Desliga","timer":{"minutos":"0","segundos":"0","milesimos":"0"},"rampa":"2","presetMax":"100","presetMin":"0","memoriaPreset":"false","lastState":"false","ON/OFF":"false"},"7":{"nome":"Saida 7","funcao":"Liga/Desliga","timer":{"minutos":"0","segundos":"0","milesimos":"0"},"rampa":"2","presetMax":"100","presetMin":"0","memoriaPreset":"false","lastState":"false","ON/OFF":"false"},"8":{"nome":"Saida 8","funcao":"Liga/Desliga","timer":{"minutos":"0","segundos":"0","milesimos":"0"},"rampa":"2","presetMax":"100","presetMin":"0","memoriaPreset":"false","lastState":"false","ON/OFF":"false"}},"mapeado":true,"valido":true},"3":{"tipo":"Rele","versao":"3.0.0b","E":{"1":{"nome":"Entrada 1","funcao":"E>>S","paralelo":{"endereco":"","canal":"","pulsoLongo":""},"automacaoCenas":{"pulsoRapido":"0","pulsoLongo":"0"},"E>>S":"-1"},"2":{"nome":"Entrada 2","funcao":"E>>S","paralelo":{"endereco":"","canal":"","pulsoLongo":""},"automacaoCenas":{"pulsoRapido":"0","pulsoLongo":"0"},"E>>S":"-1"},"3":{"nome":"Entrada 3","funcao":"E>>S","paralelo":{"endereco":"","canal":"","pulsoLongo":""},"automacaoCenas":{"pulsoRapido":"0","pulsoLongo":"0"},"E>>S":"-1"},"4":{"nome":"Entrada 4","funcao":"E>>S","paralelo":{"endereco":"","canal":"","pulsoLongo":""},"automacaoCenas":{"pulsoRapido":"0","pulsoLongo":"0"},"E>>S":"-1"},"5":{"nome":"Entrada 5","funcao":"E>>S","paralelo":{"endereco":"","canal":"","pulsoLongo":""},"automacaoCenas":{"pulsoRapido":"0","pulsoLongo":"0"},"E>>S":"-1"},"6":{"nome":"Entrada 6","funcao":"E>>S","paralelo":{"endereco":"","canal":"","pulsoLongo":""},"automacaoCenas":{"pulsoRapido":"0","pulsoLongo":"0"},"E>>S":"-1"},"7":{"nome":"Entrada 7","funcao":"E>>S","paralelo":{"endereco":"","canal":"","pulsoLongo":""},"automacaoCenas":{"pulsoRapido":"0","pulsoLongo":"0"},"E>>S":"-1"},"8":{"nome":"Entrada 8","funcao":"E>>S","paralelo":{"endereco":"","canal":"","pulsoLongo":""},"automacaoCenas":{"pulsoRapido":"0","pulsoLongo":"0"},"E>>S":"-1"}},"S":{"1":{"nome":"Iluminação Subaquática","funcao":"Liga/Desliga","timer":{"minutos":"0","segundos":"0","milesimos":"0"},"rampa":"2","presetMax":"100","presetMin":"0","memoriaPreset":"false","lastState":"true","ON/OFF":"false"},"2":{"nome":"Cascata","funcao":"Liga/Desliga","timer":{"minutos":"0","segundos":"0","milesimos":"0"},"rampa":"2","presetMax":"100","presetMin":"0","memoriaPreset":"false","lastState":"true","ON/OFF":"false"},"3":{"nome":"Borda Infinita","funcao":"Liga/Desliga","timer":{"minutos":"0","segundos":"0","milesimos":"0"},"rampa":"2","presetMax":"100","presetMin":"0","memoriaPreset":"false","lastState":"true","ON/OFF":"false"},"4":{"nome":"Saida 4","funcao":"Liga/Desliga","timer":{"minutos":"0","segundos":"0","milesimos":"0"},"rampa":"2","presetMax":"100","presetMin":"0","memoriaPreset":"false","lastState":"true","ON/OFF":"false"},"5":{"nome":"Saida 5","funcao":"Liga/Desliga","timer":{"minutos":"0","segundos":"0","milesimos":"0"},"rampa":"2","presetMax":"100","presetMin":"0","memoriaPreset":"false","lastState":"true","ON/OFF":"false"},"6":{"nome":"Saida 6","funcao":"Liga/Desliga","timer":{"minutos":"0","segundos":"0","milesimos":"0"},"rampa":"2","presetMax":"100","presetMin":"0","memoriaPreset":"false","lastState":"true","ON/OFF":"false"},"7":{"nome":"Saida 7","funcao":"Liga/Desliga","timer":{"minutos":"0","segundos":"0","milesimos":"0"},"rampa":"2","presetMax":"100","presetMin":"0","memoriaPreset":"false","lastState":"true","ON/OFF":"false"},"8":{"nome":"Saida 8","funcao":"Liga/Desliga","timer":{"minutos":"0","segundos":"0","milesimos":"0"},"rampa":"2","presetMax":"100","presetMin":"0","memoriaPreset":"false","lastState":"true","ON/OFF":"false"}},"mapeado":true,"valido":true},"4":{"tipo":"Dimmer","versao":"3.0.0b","E":{"1":{"nome":"Entrada1","funcao":"E>>S","paralelo":{"endereco":"","canal":"","pulsoLongo":""},"automacaoCenas":{"pulsoRapido":"0","pulsoLongo":"0"},"E>>S":"-1"},"2":{"nome":"Entrada 2","funcao":"E>>S","paralelo":{"endereco":"","canal":"","pulsoLongo":""},"automacaoCenas":{"pulsoRapido":"0","pulsoLongo":"0"},"E>>S":"-1"},"3":{"nome":"Entrada 3","funcao":"E>>S","paralelo":{"endereco":"","canal":"","pulsoLongo":""},"automacaoCenas":{"pulsoRapido":"0","pulsoLongo":"0"},"E>>S":"-1"},"4":{"nome":"Entrada 4","funcao":"E>>S","paralelo":{"endereco":"","canal":"","pulsoLongo":""},"automacaoCenas":{"pulsoRapido":"0","pulsoLongo":"0"},"E>>S":"-1"},"5":{"nome":"Entrada 5","funcao":"E>>S","paralelo":{"endereco":"","canal":"","pulsoLongo":""},"automacaoCenas":{"pulsoRapido":"0","pulsoLongo":"0"},"E>>S":"-1"},"6":{"nome":"Entrada 6","funcao":"E>>S","paralelo":{"endereco":"","canal":"","pulsoLongo":""},"automacaoCenas":{"pulsoRapido":"0","pulsoLongo":"0"},"E>>S":"-1"},"7":{"nome":"Entrada 7","funcao":"E>>S","paralelo":{"endereco":"","canal":"","pulsoLongo":""},"automacaoCenas":{"pulsoRapido":"0","pulsoLongo":"0"},"E>>S":"-1"},"8":{"nome":"Entrada 8","funcao":"E>>S","paralelo":{"endereco":"","canal":"","pulsoLongo":""},"automacaoCenas":{"pulsoRapido":"0","pulsoLongo":"0"},"E>>S":"-1"}},"S":{"1":{"nome":"Fita LED Home","funcao":"Liga/Desliga","timer":{"minutos":"0","segundos":"0","milesimos":"0"},"rampa":"2","presetMax":"100","presetMin":"15","memoriaPreset":"false","lastState":"true","ON/OFF":"false"},"2":{"nome":"Defray Home","funcao":"Liga/Desliga","timer":{"minutos":"0","segundos":"0","milesimos":"0"},"rampa":"2","presetMax":"100","presetMin":"0","memoriaPreset":"false","lastState":"true","ON/OFF":"true"},"3":{"nome":"Expositor","funcao":"Liga/Desliga","timer":{"minutos":"0","segundos":"0","milesimos":"0"},"rampa":"2","presetMax":"100","presetMin":"10","memoriaPreset":"false","lastState":"true","ON/OFF":"false"},"4":{"nome":"Tv","funcao":"Liga/Desliga","timer":{"minutos":"0","segundos":"0","milesimos":"0"},"rampa":"2","presetMax":"100","presetMin":"10","memoriaPreset":"false","lastState":"true","ON/OFF":"false"},"5":{"nome":"Telão","funcao":"Liga/Desliga","timer":{"minutos":"0","segundos":"0","milesimos":"0"},"rampa":"2","presetMax":"100","presetMin":"10","memoriaPreset":"false","lastState":"true","ON/OFF":"false"},"6":{"nome":"Saida 6","funcao":"Liga/Desliga","timer":{"minutos":"0","segundos":"0","milesimos":"0"},"rampa":"2","presetMax":"100","presetMin":"5","memoriaPreset":"false","lastState":"true","ON/OFF":"false"},"7":{"nome":"Saida 7","funcao":"Liga/Desliga","timer":{"minutos":"0","segundos":"0","milesimos":"0"},"rampa":"2","presetMax":"100","presetMin":"10","memoriaPreset":"false","lastState":"true","ON/OFF":"false"},"8":{"nome":"Saida8","funcao":"Liga/Desliga","timer":{"minutos":"0","segundos":"0","milesimos":"0"},"rampa":"2","presetMax":"100","presetMin":"0","memoriaPreset":"false","lastState":"true","ON/OFF":"false"}},"mapeado":true,"valido":true},"5":{"tipo":"Rele","versao":"3.0.0b","E":{"1":{"nome":"Entrada 1","funcao":"E>>S","paralelo":{"endereco":"","canal":"","pulsoLongo":""},"automacaoCenas":{"pulsoRapido":"0","pulsoLongo":"0"},"E>>S":"-1"},"2":{"nome":"Entrada 2","funcao":"E>>S","paralelo":{"endereco":"","canal":"","pulsoLongo":""},"automacaoCenas":{"pulsoRapido":"0","pulsoLongo":"0"},"E>>S":"-1"},"3":{"nome":"Entrada 3","funcao":"E>>S","paralelo":{"endereco":"","canal":"","pulsoLongo":""},"automacaoCenas":{"pulsoRapido":"0","pulsoLongo":"0"},"E>>S":"-1"},"4":{"nome":"Entrada 4","funcao":"E>>S","paralelo":{"endereco":"","canal":"","pulsoLongo":""},"automacaoCenas":{"pulsoRapido":"0","pulsoLongo":"0"},"E>>S":"-1"},"5":{"nome":"Entrada 5","funcao":"E>>S","paralelo":{"endereco":"","canal":"","pulsoLongo":""},"automacaoCenas":{"pulsoRapido":"0","pulsoLongo":"0"},"E>>S":"-1"},"6":{"nome":"Entrada 6","funcao":"E>>S","paralelo":{"endereco":"","canal":"","pulsoLongo":""},"automacaoCenas":{"pulsoRapido":"0","pulsoLongo":"0"},"E>>S":"-1"},"7":{"nome":"Entrada 7","funcao":"E>>S","paralelo":{"endereco":"","canal":"","pulsoLongo":""},"automacaoCenas":{"pulsoRapido":"0","pulsoLongo":"0"},"E>>S":"-1"},"8":{"nome":"Entrada 8","funcao":"E>>S","paralelo":{"endereco":"","canal":"","pulsoLongo":""},"automacaoCenas":{"pulsoRapido":"0","pulsoLongo":"0"},"E>>S":"-1"}},"S":{"1":{"nome":"Saida 1","funcao":"Liga/Desliga","timer":{"minutos":"0","segundos":"0","milesimos":"0"},"rampa":"2","presetMax":"100","presetMin":"0","memoriaPreset":"false","lastState":"true","ON/OFF":"false"},"2":{"nome":"Saida 2","funcao":"Liga/Desliga","timer":{"minutos":"0","segundos":"0","milesimos":"0"},"rampa":"2","presetMax":"100","presetMin":"0","memoriaPreset":"false","lastState":"true","ON/OFF":"false"},"3":{"nome":"Saida 3","funcao":"Liga/Desliga","timer":{"minutos":"0","segundos":"0","milesimos":"0"},"rampa":"2","presetMax":"100","presetMin":"0","memoriaPreset":"false","lastState":"true","ON/OFF":"false"},"4":{"nome":"Saida 4","funcao":"Liga/Desliga","timer":{"minutos":"0","segundos":"0","milesimos":"0"},"rampa":"2","presetMax":"100","presetMin":"0","memoriaPreset":"false","lastState":"true","ON/OFF":"false"},"5":{"nome":"Saida 5","funcao":"Liga/Desliga","timer":{"minutos":"0","segundos":"0","milesimos":"0"},"rampa":"2","presetMax":"100","presetMin":"0","memoriaPreset":"false","lastState":"true","ON/OFF":"false"},"6":{"nome":"Saida6","funcao":"Liga/Desliga","timer":{"minutos":"0","segundos":"0","milesimos":"0"},"rampa":"2","presetMax":"100","presetMin":"0","memoriaPreset":"false","lastState":"true","ON/OFF":"false"},"7":{"nome":"Saida 7","funcao":"Liga/Desliga","timer":{"minutos":"0","segundos":"0","milesimos":"0"},"rampa":"2","presetMax":"100","presetMin":"0","memoriaPreset":"false","lastState":"true","ON/OFF":"false"},"8":{"nome":"Saida 8","funcao":"Liga/Desliga","timer":{"minutos":"0","segundos":"0","milesimos":"0"},"rampa":"2","presetMax":"100","presetMin":"0","memoriaPreset":"false","lastState":"true","ON/OFF":"false"}},"mapeado":true,"valido":true},"6":{"tipo":"Rele","versao":"3.0.0b","E":{"1":{"nome":"Entrada 1","funcao":"E>>S","paralelo":{"endereco":"","canal":"","pulsoLongo":""},"automacaoCenas":{"pulsoRapido":"0","pulsoLongo":"0"},"E>>S":"-1"},"2":{"nome":"Entrada 2","funcao":"E>>S","paralelo":{"endereco":"","canal":"","pulsoLongo":""},"automacaoCenas":{"pulsoRapido":"0","pulsoLongo":"0"},"E>>S":"-1"},"3":{"nome":"Entrada 3","funcao":"E>>S","paralelo":{"endereco":"","canal":"","pulsoLongo":""},"automacaoCenas":{"pulsoRapido":"0","pulsoLongo":"0"},"E>>S":"-1"},"4":{"nome":"Entrada4","funcao":"E>>S","paralelo":{"endereco":"","canal":"","pulsoLongo":""},"automacaoCenas":{"pulsoRapido":"0","pulsoLongo":"0"},"E>>S":"-1"},"5":{"nome":"Entrada 5","funcao":"E>>S","paralelo":{"endereco":"","canal":"","pulsoLongo":""},"automacaoCenas":{"pulsoRapido":"0","pulsoLongo":"0"},"E>>S":"-1"},"6":{"nome":"Entrada6","funcao":"E>>S","paralelo":{"endereco":"","canal":"","pulsoLongo":""},"automacaoCenas":{"pulsoRapido":"0","pulsoLongo":"0"},"E>>S":"-1"},"7":{"nome":"Entrada 7","funcao":"E>>S","paralelo":{"endereco":"","canal":"","pulsoLongo":""},"automacaoCenas":{"pulsoRapido":"0","pulsoLongo":"0"},"E>>S":"-1"},"8":{"nome":"Entrada 8","funcao":"E>>S","paralelo":{"endereco":"","canal":"","pulsoLongo":""},"automacaoCenas":{"pulsoRapido":"0","pulsoLongo":"0"},"E>>S":"-1"}},"S":{"1":{"nome":"Saida 1","funcao":"Liga/Desliga","timer":{"minutos":"0","segundos":"0","milesimos":"0"},"rampa":"2","presetMax":"100","presetMin":"0","memoriaPreset":"false","lastState":"true","ON/OFF":"false"},"2":{"nome":"Saida 2","funcao":"Liga/Desliga","timer":{"minutos":"0","segundos":"0","milesimos":"0"},"rampa":"2","presetMax":"100","presetMin":"0","memoriaPreset":"false","lastState":"true","ON/OFF":"false"},"3":{"nome":"Saida 3","funcao":"Liga/Desliga","timer":{"minutos":"0","segundos":"0","milesimos":"0"},"rampa":"2","presetMax":"100","presetMin":"0","memoriaPreset":"false","lastState":"true","ON/OFF":"false"},"4":{"nome":"Saida 4","funcao":"Liga/Desliga","timer":{"minutos":"0","segundos":"0","milesimos":"0"},"rampa":"2","presetMax":"100","presetMin":"0","memoriaPreset":"false","lastState":"true","ON/OFF":"false"},"5":{"nome":"Saida 5","funcao":"Liga/Desliga","timer":{"minutos":"0","segundos":"0","milesimos":"0"},"rampa":"2","presetMax":"100","presetMin":"0","memoriaPreset":"false","lastState":"true","ON/OFF":"false"},"6":{"nome":"Saida 6","funcao":"Liga/Desliga","timer":{"minutos":"0","segundos":"0","milesimos":"0"},"rampa":"2","presetMax":"100","presetMin":"0","memoriaPreset":"false","lastState":"true","ON/OFF":"false"},"7":{"nome":"Saida 7","funcao":"Liga/Desliga","timer":{"minutos":"0","segundos":"3","milesimos":"0"},"rampa":"2","presetMax":"100","presetMin":"0","memoriaPreset":"false","lastState":"false","ON/OFF":"false"},"8":{"nome":"Saida 8","funcao":"Liga/Desliga","timer":{"minutos":"0","segundos":"0","milesimos":"0"},"rampa":"2","presetMax":"100","presetMin":"0","memoriaPreset":"false","lastState":"true","ON/OFF":"false"}},"mapeado":true,"valido":true},"7":{"tipo":"Rele","versao":"3.0.0b","E":{"1":{"nome":"Entrada 1","funcao":"automacaoSensor","paralelo":{"endereco":"","canal":"","pulsoLongo":""},"automacaoCenas":{"pulsoRapido":"0","pulsoLongo":"0"},"E>>S":"-1"},"2":{"nome":"Entrada 2","funcao":"automacaoSensor","paralelo":{"endereco":"","canal":"","pulsoLongo":""},"automacaoCenas":{"pulsoRapido":"0","pulsoLongo":"0"},"E>>S":"-1"},"3":{"nome":"Entrada3","funcao":"automacaoSensor","paralelo":{"endereco":"","canal":"","pulsoLongo":""},"automacaoCenas":{"pulsoRapido":"0","pulsoLongo":"0"},"E>>S":"-1"},"4":{"nome":"Entrada 4","funcao":"automacaoSensor","paralelo":{"endereco":"","canal":"","pulsoLongo":""},"automacaoCenas":{"pulsoRapido":"0","pulsoLongo":"0"},"E>>S":"-1"},"5":{"nome":"Entrada5","funcao":"E>>S","paralelo":{"endereco":"","canal":"","pulsoLongo":""},"automacaoCenas":{"pulsoRapido":"0","pulsoLongo":"0"},"E>>S":"-1"},"6":{"nome":"Entrada 6","funcao":"E>>S","paralelo":{"endereco":"","canal":"","pulsoLongo":""},"automacaoCenas":{"pulsoRapido":"0","pulsoLongo":"0"},"E>>S":"-1"},"7":{"nome":"Entrada 7","funcao":"E>>S","paralelo":{"endereco":"","canal":"","pulsoLongo":""},"automacaoCenas":{"pulsoRapido":"0","pulsoLongo":"0"},"E>>S":"-1"},"8":{"nome":"Entrada 8","funcao":"E>>S","paralelo":{"endereco":"","canal":"","pulsoLongo":""},"automacaoCenas":{"pulsoRapido":"0","pulsoLongo":"0"},"E>>S":"-1"}},"S":{"1":{"nome":"Saida1","funcao":"Liga/Desliga","timer":{"minutos":"0","segundos":"0","milesimos":"0"},"rampa":"2","presetMax":"100","presetMin":"0","memoriaPreset":"false","lastState":"false","ON/OFF":"false"},"2":{"nome":"Saida 2","funcao":"Liga/Desliga","timer":{"minutos":"0","segundos":"0","milesimos":"0"},"rampa":"2","presetMax":"100","presetMin":"0","memoriaPreset":"false","lastState":"false","ON/OFF":"false"},"3":{"nome":"Saida 3","funcao":"Liga/Desliga","timer":{"minutos":"0","segundos":"0","milesimos":"0"},"rampa":"2","presetMax":"100","presetMin":"0","memoriaPreset":"false","lastState":"false","ON/OFF":"false"},"4":{"nome":"Saida 4","funcao":"Liga/Desliga","timer":{"minutos":"0","segundos":"0","milesimos":"0"},"rampa":"2","presetMax":"100","presetMin":"0","memoriaPreset":"false","lastState":"false","ON/OFF":"false"},"5":{"nome":"Saida 5","funcao":"Liga/Desliga","timer":{"minutos":"0","segundos":"0","milesimos":"0"},"rampa":"2","presetMax":"100","presetMin":"0","memoriaPreset":"false","lastState":"false","ON/OFF":"false"},"6":{"nome":"Saida 6","funcao":"Liga/Desliga","timer":{"minutos":"0","segundos":"0","milesimos":"0"},"rampa":"2","presetMax":"100","presetMin":"0","memoriaPreset":"false","lastState":"false","ON/OFF":"false"},"7":{"nome":"Saida 7","funcao":"Liga/Desliga","timer":{"minutos":"0","segundos":"0","milesimos":"0"},"rampa":"2","presetMax":"100","presetMin":"0","memoriaPreset":"false","lastState":"false","ON/OFF":"false"},"8":{"nome":"Saida 8","funcao":"Liga/Desliga","timer":{"minutos":"0","segundos":"0","milesimos":"0"},"rampa":"2","presetMax":"100","presetMin":"0","memoriaPreset":"false","lastState":"false","ON/OFF":"false"}},"mapeado":true,"valido":true},"8":{"tipo":"Rele","versao":"3.0.0b","E":{"1":{"nome":"Entrada 1","funcao":"E>>S","paralelo":{"endereco":"","canal":"","pulsoLongo":""},"automacaoCenas":{"pulsoRapido":"0","pulsoLongo":"0"},"E>>S":"-1"},"2":{"nome":"Entrada 2","funcao":"E>>S","paralelo":{"endereco":"","canal":"","pulsoLongo":""},"automacaoCenas":{"pulsoRapido":"0","pulsoLongo":"0"},"E>>S":"-1"},"3":{"nome":"Entrada 3","funcao":"E>>S","paralelo":{"endereco":"","canal":"","pulsoLongo":""},"automacaoCenas":{"pulsoRapido":"0","pulsoLongo":"0"},"E>>S":"-1"},"4":{"nome":"Entrada 4","funcao":"E>>S","paralelo":{"endereco":"","canal":"","pulsoLongo":""},"automacaoCenas":{"pulsoRapido":"0","pulsoLongo":"0"},"E>>S":"-1"},"5":{"nome":"Entrada 5","funcao":"E>>S","paralelo":{"endereco":"","canal":"","pulsoLongo":""},"automacaoCenas":{"pulsoRapido":"0","pulsoLongo":"0"},"E>>S":"-1"},"6":{"nome":"Entrada 6","funcao":"E>>S","paralelo":{"endereco":"","canal":"","pulsoLongo":""},"automacaoCenas":{"pulsoRapido":"0","pulsoLongo":"0"},"E>>S":"-1"},"7":{"nome":"Entrada 7","funcao":"E>>S","paralelo":{"endereco":"","canal":"","pulsoLongo":""},"automacaoCenas":{"pulsoRapido":"0","pulsoLongo":"0"},"E>>S":"-1"},"8":{"nome":"Entrada8","funcao":"E>>S","paralelo":{"endereco":"","canal":"","pulsoLongo":""},"automacaoCenas":{"pulsoRapido":"0","pulsoLongo":"0"},"E>>S":"-1"}},"S":{"1":{"nome":"Saida 1","funcao":"Liga/Desliga","timer":{"minutos":"0","segundos":"0","milesimos":"0"},"rampa":"2","presetMax":"100","presetMin":"0","memoriaPreset":"false","lastState":"false","ON/OFF":"false"},"2":{"nome":"Saida 2","funcao":"Liga/Desliga","timer":{"minutos":"0","segundos":"0","milesimos":"0"},"rampa":"2","presetMax":"100","presetMin":"0","memoriaPreset":"false","lastState":"false","ON/OFF":"false"},"3":{"nome":"Saida 3","funcao":"Liga/Desliga","timer":{"minutos":"0","segundos":"0","milesimos":"0"},"rampa":"2","presetMax":"100","presetMin":"0","memoriaPreset":"false","lastState":"false","ON/OFF":"false"},"4":{"nome":"Saida 4","funcao":"Liga/Desliga","timer":{"minutos":"0","segundos":"0","milesimos":"0"},"rampa":"2","presetMax":"100","presetMin":"0","memoriaPreset":"false","lastState":"false","ON/OFF":"false"},"5":{"nome":"Saida5","funcao":"Liga/Desliga","timer":{"minutos":"0","segundos":"0","milesimos":"0"},"rampa":"2","presetMax":"100","presetMin":"0","memoriaPreset":"false","lastState":"false","ON/OFF":"false"},"6":{"nome":"Saida 6","funcao":"Liga/Desliga","timer":{"minutos":"0","segundos":"0","milesimos":"0"},"rampa":"2","presetMax":"100","presetMin":"0","memoriaPreset":"false","lastState":"false","ON/OFF":"false"},"7":{"nome":"Saida 7","funcao":"Liga/Desliga","timer":{"minutos":"0","segundos":"0","milesimos":"0"},"rampa":"2","presetMax":"100","presetMin":"0","memoriaPreset":"false","lastState":"false","ON/OFF":"false"},"8":{"nome":"Saida 8","funcao":"Liga/Desliga","timer":{"minutos":"0","segundos":"0","milesimos":"0"},"rampa":"2","presetMax":"100","presetMin":"0","memoriaPreset":"false","lastState":"false","ON/OFF":"false"}},"mapeado":true,"valido":true},"9":{"tipo":"Rele","versao":"3.0.0b","E":{"1":{"nome":"Entrada 1","funcao":"E>>S","paralelo":{"endereco":"","canal":"","pulsoLongo":""},"automacaoCenas":{"pulsoRapido":"0","pulsoLongo":"0"},"E>>S":"-1"},"2":{"nome":"Entrada 2","funcao":"E>>S","paralelo":{"endereco":"","canal":"","pulsoLongo":""},"automacaoCenas":{"pulsoRapido":"0","pulsoLongo":"0"},"E>>S":"-1"},"3":{"nome":"Entrada3","funcao":"E>>S","paralelo":{"endereco":"","canal":"","pulsoLongo":""},"automacaoCenas":{"pulsoRapido":"0","pulsoLongo":"0"},"E>>S":"-1"},"4":{"nome":"Entrada4","funcao":"E>>S","paralelo":{"endereco":"","canal":"","pulsoLongo":""},"automacaoCenas":{"pulsoRapido":"0","pulsoLongo":"0"},"E>>S":"-1"},"5":{"nome":"Entrada 5","funcao":"E>>S","paralelo":{"endereco":"","canal":"","pulsoLongo":""},"automacaoCenas":{"pulsoRapido":"0","pulsoLongo":"0"},"E>>S":"-1"},"6":{"nome":"Entrada 6","funcao":"E>>S","paralelo":{"endereco":"","canal":"","pulsoLongo":""},"automacaoCenas":{"pulsoRapido":"0","pulsoLongo":"0"},"E>>S":"-1"},"7":{"nome":"Entrada 7","funcao":"E>>S","paralelo":{"endereco":"","canal":"","pulsoLongo":""},"automacaoCenas":{"pulsoRapido":"0","pulsoLongo":"0"},"E>>S":"-1"},"8":{"nome":"Entrada 8","funcao":"E>>S","paralelo":{"endereco":"","canal":"","pulsoLongo":""},"automacaoCenas":{"pulsoRapido":"0","pulsoLongo":"0"},"E>>S":"-1"}},"S":{"1":{"nome":"Saida 1","funcao":"Liga/Desliga","timer":{"minutos":"0","segundos":"0","milesimos":"0"},"rampa":"2","presetMax":"100","presetMin":"0","memoriaPreset":"false","lastState":"false","ON/OFF":"false"},"2":{"nome":"Saida 2","funcao":"Liga/Desliga","timer":{"minutos":"0","segundos":"0","milesimos":"0"},"rampa":"2","presetMax":"100","presetMin":"0","memoriaPreset":"false","lastState":"false","ON/OFF":"false"},"3":{"nome":"Saida 3","funcao":"Liga/Desliga","timer":{"minutos":"0","segundos":"0","milesimos":"0"},"rampa":"2","presetMax":"100","presetMin":"0","memoriaPreset":"false","lastState":"false","ON/OFF":"false"},"4":{"nome":"Saida 4","funcao":"Liga/Desliga","timer":{"minutos":"0","segundos":"0","milesimos":"0"},"rampa":"2","presetMax":"100","presetMin":"0","memoriaPreset":"false","lastState":"false","ON/OFF":"false"},"5":{"nome":"Saida 5","funcao":"Liga/Desliga","timer":{"minutos":"0","segundos":"0","milesimos":"0"},"rampa":"2","presetMax":"100","presetMin":"0","memoriaPreset":"false","lastState":"true","ON/OFF":"false"},"6":{"nome":"Saida 6","funcao":"Liga/Desliga","timer":{"minutos":"0","segundos":"0","milesimos":"0"},"rampa":"2","presetMax":"100","presetMin":"0","memoriaPreset":"false","lastState":"false","ON/OFF":"false"},"7":{"nome":"Saida 7","funcao":"Liga/Desliga","timer":{"minutos":"0","segundos":"0","milesimos":"0"},"rampa":"2","presetMax":"100","presetMin":"0","memoriaPreset":"false","lastState":"false","ON/OFF":"false"},"8":{"nome":"Saida 8","funcao":"Liga/Desliga","timer":{"minutos":"0","segundos":"0","milesimos":"0"},"rampa":"2","presetMax":"100","presetMin":"0","memoriaPreset":"false","lastState":"false","ON/OFF":"false"}},"mapeado":true,"valido":true},"10":{"tipo":"Rele","versao":"3.0.0b","E":{"1":{"nome":"Entrada 1","funcao":"E>>S","paralelo":{"endereco":"","canal":"","pulsoLongo":""},"automacaoCenas":{"pulsoRapido":"0","pulsoLongo":"0"},"E>>S":"-1"},"2":{"nome":"Entrada 2","funcao":"E>>S","paralelo":{"endereco":"","canal":"","pulsoLongo":""},"automacaoCenas":{"pulsoRapido":"0","pulsoLongo":"0"},"E>>S":"-1"},"3":{"nome":"Entrada 3","funcao":"E>>S","paralelo":{"endereco":"","canal":"","pulsoLongo":""},"automacaoCenas":{"pulsoRapido":"0","pulsoLongo":"0"},"E>>S":"-1"},"4":{"nome":"Entrada 4","funcao":"E>>S","paralelo":{"endereco":"","canal":"","pulsoLongo":""},"automacaoCenas":{"pulsoRapido":"0","pulsoLongo":"0"},"E>>S":"-1"},"5":{"nome":"Entrada 5","funcao":"E>>S","paralelo":{"endereco":"","canal":"","pulsoLongo":""},"automacaoCenas":{"pulsoRapido":"0","pulsoLongo":"0"},"E>>S":"-1"},"6":{"nome":"Entrada 6","funcao":"E>>S","paralelo":{"endereco":"","canal":"","pulsoLongo":""},"automacaoCenas":{"pulsoRapido":"0","pulsoLongo":"0"},"E>>S":"-1"},"7":{"nome":"Entrada 7","funcao":"E>>S","paralelo":{"endereco":"","canal":"","pulsoLongo":""},"automacaoCenas":{"pulsoRapido":"0","pulsoLongo":"0"},"E>>S":"-1"},"8":{"nome":"Entrada 8","funcao":"E>>S","paralelo":{"endereco":"","canal":"","pulsoLongo":""},"automacaoCenas":{"pulsoRapido":"0","pulsoLongo":"0"},"E>>S":"-1"}},"S":{"1":{"nome":"Saida 1","funcao":"Liga/Desliga","timer":{"minutos":"0","segundos":"0","milesimos":"0"},"rampa":"2","presetMax":"100","presetMin":"0","memoriaPreset":"false","lastState":"false","ON/OFF":"false"},"2":{"nome":"Saida 2","funcao":"Liga/Desliga","timer":{"minutos":"0","segundos":"0","milesimos":"0"},"rampa":"2","presetMax":"100","presetMin":"0","memoriaPreset":"false","lastState":"false","ON/OFF":"false"},"3":{"nome":"Saida 3","funcao":"Liga/Desliga","timer":{"minutos":"0","segundos":"0","milesimos":"0"},"rampa":"2","presetMax":"100","presetMin":"0","memoriaPreset":"false","lastState":"false","ON/OFF":"false"},"4":{"nome":"Saida 4","funcao":"Liga/Desliga","timer":{"minutos":"0","segundos":"0","milesimos":"0"},"rampa":"2","presetMax":"100","presetMin":"0","memoriaPreset":"false","lastState":"false","ON/OFF":"false"},"5":{"nome":"Saida 5","funcao":"Liga/Desliga","timer":{"minutos":"0","segundos":"0","milesimos":"0"},"rampa":"2","presetMax":"100","presetMin":"0","memoriaPreset":"false","lastState":"false","ON/OFF":"false"},"6":{"nome":"Saida 6","funcao":"Liga/Desliga","timer":{"minutos":"0","segundos":"0","milesimos":"0"},"rampa":"2","presetMax":"100","presetMin":"0","memoriaPreset":"false","lastState":"false","ON/OFF":"false"},"7":{"nome":"Saida 7","funcao":"Liga/Desliga","timer":{"minutos":"0","segundos":"0","milesimos":"0"},"rampa":"2","presetMax":"100","presetMin":"0","memoriaPreset":"false","lastState":"false","ON/OFF":"false"},"8":{"nome":"Saida 8","funcao":"Liga/Desliga","timer":{"minutos":"0","segundos":"0","milesimos":"0"},"rampa":"2","presetMax":"100","presetMin":"0","memoriaPreset":"false","lastState":"false","ON/OFF":"false"}},"mapeado":true,"valido":true}},"ambientes":{"1":{"nome":"Sala De Estar","dispositivos":["M4C1S","M4C2S","M4C3S","M4C4S","M4C5S","C1","C2"]},"2":{"nome":"Varanda","dispositivos":["M1C1S","M1C2S","M1C3S","M1C4S","C3"]},"3":{"nome":"Piscina","dispositivos":["M3C1S","M3C2S","M3C3S"]}},"usuarios":{"1":{"nome":"jordyfaria0@gmail.com","remoto":"false","exclusoes":[]},"2":{"nome":"teste2@gmail.com","remoto":"false","exclusoes":[]},"3":{"nome":"leandro@eonix.com.br","remoto":"true","exclusoes":[]},"4":{"nome":"leandro@2e.com","remoto":"true","exclusoes":[]},"5":{"nome":"leandro@a.com","remoto":"true","exclusoes":[]},"6":{"nome":"leandro@b.com","remoto":"true","exclusoes":[]},"7":{"nome":"leandro@c.com","remoto":"true","exclusoes":[]},"8":{"nome":"augustoleandro@gmail.com","remoto":"true","exclusoes":[]}}}